Metadata-Version: 1.1
Name: ssbio
Version: 0.9.9.8.post1
Summary: Tools to enable structural systems biology
Home-page: http://github.com/SBRG/ssbio
Author: Nathan Mih
Author-email: nmih@ucsd.edu
License: MIT
Download-URL: https://github.com/SBRG/ssbio/archive/v0.9.9.8.post1.tar.gz
Platform: UNKNOWN
